dearpygui_async/__about__.py
dearpygui_async/__init__.py
dearpygui_async/dearpygui_async.py
dearpygui_async-0.1.2.dist-info/METADATA
dearpygui_async-0.1.2.dist-info/WHEEL
dearpygui_async-0.1.2.dist-info/licenses/LICENSE.txt
dearpygui_async-0.1.2.dist-info/RECORD
