Metadata-Version: 2.1
Name: dearpygui-async
Version: 0.1.2
Summary: An async helper for dearpygui
Project-URL: Documentation, https://github.com/CasuallyCalm/dearpygui-async#readme
Project-URL: Issues, https://github.com/CasuallyCalm/dearpygui-async/issues
Project-URL: Source, https://github.com/CasuallyCalm/dearpygui-async
Author-email: CasuallyCalm <void@some.where>
License-Expression: MIT
License-File: LICENSE.txt
Keywords: async,asyncio,dearpygui,desktop,gui,python
Classifier: Development Status :: 4 - Beta
Classifier: Framework :: AsyncIO
Classifier: Programming Language :: Python
Classifier: Programming Language :: Python :: 3.8
Classifier: Programming Language :: Python :: 3.9
Classifier: Programming Language :: Python :: 3.10
Classifier: Programming Language :: Python :: 3.11
Classifier: Programming Language :: Python :: 3.12
Classifier: Programming Language :: Python :: Implementation :: CPython
Classifier: Programming Language :: Python :: Implementation :: PyPy
Requires-Python: >=3.8
